game_of_thrones/main.py
game_of_thrones/__init__.py
game_of_thrones-0.1.7.dist-info/entry_points.txt
game_of_thrones-0.1.7.dist-info/top_level.txt
game_of_thrones-0.1.7.dist-info/METADATA
game_of_thrones-0.1.7.dist-info/DESCRIPTION.rst
game_of_thrones-0.1.7.dist-info/metadata.json
game_of_thrones-0.1.7.dist-info/WHEEL
game_of_thrones-0.1.7.dist-info/RECORD
